src/__init__.py
src/ammos.py
src/armours.py
src/guns.py
src/main.py
src/tank.py
wot_alexaltai-0.0.1.dist-info/LICENSE
wot_alexaltai-0.0.1.dist-info/METADATA
wot_alexaltai-0.0.1.dist-info/WHEEL
wot_alexaltai-0.0.1.dist-info/top_level.txt
wot_alexaltai-0.0.1.dist-info/RECORD
