Metadata-Version: 2.1
Name: wot-alexaltai
Version: 0.0.1
Summary: WoT Build Simple Game
Home-page: https://github.com/AlexAltaitsev/WoT
Author: Alex Altaitsev
Author-email: altaitsiev@gmail.com
License: UNKNOWN
Platform: UNKNOWN
Classifier: Programming Language :: Python :: 3.8
Classifier: License :: OSI Approved :: MIT License
Classifier: Operating System :: OS Independent
Requires-Python: >=3.6
